disco.cpython-310-powerpc64le-linux-gnu.so
discodisco-0.1.2.dist-info/LICENSE
discodisco-0.1.2.dist-info/METADATA
discodisco-0.1.2.dist-info/top_level.txt
discodisco-0.1.2.dist-info/RECORD
discodisco-0.1.2.dist-info/entry_points.txt
discodisco-0.1.2.dist-info/WHEEL
discodisco.libs/libasound-f637e935.so.2.0.0
discodisco/disco.py
discodisco/__init__.py
discodisco/cli.py
